{
	"configurations" : 
	[
		{
			"directories" : 
			[
				{
					"build" : ".",
					"hasInstallRule" : true,
					"jsonFile" : "directory-.-d8a0cbe20b475832d7e5.json",
					"minimumCMakeVersion" : 
					{
						"string" : "3.12"
					},
					"projectIndex" : 0,
					"source" : ".",
					"targetIndexes" : 
					[
						0,
						1
					]
				}
			],
			"name" : "",
			"projects" : 
			[
				{
					"directoryIndexes" : 
					[
						0
					],
					"name" : "science",
					"targetIndexes" : 
					[
						0,
						1
					]
				}
			],
			"targets" : 
			[
				{
					"directoryIndex" : 0,
					"id" : "science_uninstall::@6890427a1f51a3e7e1df",
					"jsonFile" : "target-science_uninstall-55a2693dbbc9ce506cec.json",
					"name" : "science_uninstall",
					"projectIndex" : 0
				},
				{
					"directoryIndex" : 0,
					"id" : "uninstall::@6890427a1f51a3e7e1df",
					"jsonFile" : "target-uninstall-a27e0e53bb9ca6cf6610.json",
					"name" : "uninstall",
					"projectIndex" : 0
				}
			]
		}
	],
	"kind" : "codemodel",
	"paths" : 
	{
		"build" : "/home/ender/CUB-URC/2026-Rover-Code/ros2_ws/build/science",
		"source" : "/home/ender/CUB-URC/2026-Rover-Code/ros2_ws/src_new/science"
	},
	"version" : 
	{
		"major" : 2,
		"minor" : 3
	}
}
